{
	"info": {
		"_postman_id": "24c2310a-a21a-472b-8e48-964a4bd08dc5",
		"name": "Finance Tracker",
		"schema": "https://schema.getpostman.com/json/collection/v2.1.0/collection.json"
	},
	"item": [
		{
			"name": "Spendings by userid",
			"request": {
				"method": "GET",
				"header": [
					{
						"key": "Authorization",
						"value": "Bearer fc721b7a-f221-47c1-9d5e-5ab24e9682ab",
						"type": "text"
					}
				],
				"body": {
					"mode": "raw",
					"raw": ""
				},
				"url": {
					"raw": "http://localhost:8080/spendings?userId=2",
					"protocol": "http",
					"host": [
						"localhost"
					],
					"port": "8080",
					"path": [
						"spendings"
					],
					"query": [
						{
							"key": "userId",
							"value": "2"
						}
					]
				}
			},
			"response": []
		},
		{
			"name": "Login",
			"request": {
				"method": "POST",
				"header": [
					{
						"key": "Content-Type",
						"name": "Content-Type",
						"value": "application/json",
						"type": "text"
					}
				],
				"body": {
					"mode": "raw",
					"raw": "{\n\t\"email\": \"janhasler01@gmail.com\",\n\t\"password\": \"123456\"\n}"
				},
				"url": {
					"raw": "http://localhost:8080/login",
					"protocol": "http",
					"host": [
						"localhost"
					],
					"port": "8080",
					"path": [
						"login"
					]
				}
			},
			"response": []
		},
		{
			"name": "Logout",
			"request": {
				"method": "DELETE",
				"header": [
					{
						"key": "Authorization",
						"value": "fc721b7a-f221-47c1-9d5e-5ab24e9682ab",
						"type": "text"
					}
				],
				"body": {
					"mode": "raw",
					"raw": ""
				},
				"url": {
					"raw": "http://localhost:8080/login",
					"protocol": "http",
					"host": [
						"localhost"
					],
					"port": "8080",
					"path": [
						"login"
					],
					"query": [
						{
							"key": "",
							"value": ""
						}
					]
				}
			},
			"response": []
		}
	]
}